py_recommendation/__init__.py
py_recommendation/constants.py
py_recommendation/data.py
py_recommendation/error.py
py_recommendation/input_data.py
py_recommendation/item_profile.py
py_recommendation/py_recosys.py
py_recommendation/reco_cred.py
py_recommendation/user_profile.py
py_recommendation/utils.py
py_recommendation-0.1.5.dist-info/LICENSE
py_recommendation-0.1.5.dist-info/METADATA
py_recommendation-0.1.5.dist-info/WHEEL
py_recommendation-0.1.5.dist-info/top_level.txt
py_recommendation-0.1.5.dist-info/RECORD
