Metadata-Version: 2.1
Name: py-recommendation
Version: 0.1.5
Summary: A library that provides an easy ready-to-use Recommendation engine.
Home-page: https://github.com/kashy750/RecoSystem
Author: Kashyap Madariyil
Author-email: kashyapmadariyil@gmail.com
Maintainer: Kashyap Madariyil
Maintainer-email: kashyapmadariyil@gmail.com
License: MIT License
Download-URL: https://pypi.org/project/py-recommendation/
Keywords: recommender system recommendation engine
Platform: Any
Classifier: Intended Audience :: Developers
Classifier: License :: OSI Approved :: MIT License
Classifier: Operating System :: OS Independent
Classifier: Topic :: Software Development :: Libraries :: Python Modules
Classifier: Programming Language :: Python
Classifier: Programming Language :: Python :: 3
Classifier: Programming Language :: Python :: 3.5
Classifier: Programming Language :: Python :: 3.6
Classifier: Programming Language :: Python :: 3.7
Classifier: Programming Language :: Python :: 3.8
Requires-Python: >=3.5
Requires-Dist: scikit-learn (==0.22.1)
Requires-Dist: pandas (>=1.0.3)
Requires-Dist: numpy (>=1.18.4)
